Metadata-Version: 2.1
Name: pdf-fp
Version: 1.1
Summary: Gaussian and Binomial Distributions
Home-page: UNKNOWN
Author: Abdelrahman Omran
Author-email: apdo.omran@gmail.com
License: UNKNOWN
Platform: UNKNOWN
